sqdiv/__init__.py
sqdiv-0.1.dist-info/METADATA
sqdiv-0.1.dist-info/RECORD
sqdiv-0.1.dist-info/WHEEL
sqdiv-0.1.dist-info/top_level.txt
