Metadata-Version: 2.1
Name: sqdiv
Version: 0.1
Summary: A small utility to compute the squarest pair of divisors for an integer.
Home-page: https://github.com/ericmjl/squarest-divisors
Author: UNKNOWN
Author-email: ericmajinglong@gmail.com
License: MIT
Keywords: math,geometry,matplotlib
Platform: UNKNOWN
Classifier: Topic :: Scientific/Engineering :: Visualization
Requires-Dist: numpy
Requires-Dist: hypothesis
